xlwings_utils/__init__.py
xlwings_utils/dropbox.py
xlwings_utils/github.py
xlwings_utils/local.py
xlwings_utils/nextcloud.py
xlwings_utils/xlwings_utils.py
xlwings_utils-26.0.3.dist-info/METADATA
xlwings_utils-26.0.3.dist-info/WHEEL
xlwings_utils-26.0.3.dist-info/top_level.txt
xlwings_utils-26.0.3.dist-info/RECORD
