Metadata-Version: 2.4
Name: xlwings_utils
Version: 26.0.3
Summary: xlwings_utils
Author-email: Ruud van der Ham <rt.van.der.ham@gmail.com>
Project-URL: Homepage, https://github.com/salabim/xlwings_utils
Project-URL: Repository, https://github.com/salabim/xlwings_utils
Classifier: Development Status :: 5 - Production/Stable
Classifier: Programming Language :: Python :: 3 :: Only
Requires-Python: >=3.9
Requires-Dist: requests
